ogr2wkt/__init__.py
ogr2wkt/__version__.py
ogr2wkt/cli.py
ogr2wkt/util.py
ogr2wkt-0.0.2.dist-info/LICENSE
ogr2wkt-0.0.2.dist-info/METADATA
ogr2wkt-0.0.2.dist-info/WHEEL
ogr2wkt-0.0.2.dist-info/entry_points.txt
ogr2wkt-0.0.2.dist-info/top_level.txt
ogr2wkt-0.0.2.dist-info/RECORD
