Metadata-Version: 2.1
Name: ogr2wkt
Version: 0.0.2
Summary: Convert (Fiona-supported) OGR data sources to plaintext WKT.
Home-page: https://github.com/tomplex/ogr2wkt
Author: Tom Caruso
Author-email: carusot42@gmail.com
License: MIT
Platform: UNKNOWN
Classifier: License :: OSI Approved :: MIT License
Classifier: Programming Language :: Python
Classifier: Programming Language :: Python :: 3
Classifier: Programming Language :: Python :: 3.5
Classifier: Programming Language :: Python :: 3.6
Classifier: Programming Language :: Python :: 3.7
Classifier: Programming Language :: Python :: 3.8
Classifier: Programming Language :: Python :: Implementation :: CPython
Classifier: Topic :: Scientific/Engineering :: GIS
Requires-Python: >=3.5.0
Requires-Dist: fiona
Requires-Dist: geomet
Requires-Dist: click
